odoo_models_connect/__init__.py
odoo_models_connect/connect_odoo.py
odoo_models_connect/decorators.py
odoo_models_connect/exceptions.py
odoo_models_connect/fields.py
odoo_models_connect/models.py
odoo_models_connect/utils.py
odoo_models_connect-0.1.15.dist-info/METADATA
odoo_models_connect-0.1.15.dist-info/WHEEL
odoo_models_connect-0.1.15.dist-info/top_level.txt
odoo_models_connect-0.1.15.dist-info/RECORD
