Metadata-Version: 2.1
Name: odoo-models-connect
Version: 0.1.15
Summary: Library to improve interaction and communication with odoo for integration with other technologies.
Home-page: https://github.com/DeijoseDevelop/odoo_models_connect
Author: Deiver Jose Vazquez Moreno
Author-email: estudiandovazmore@gmail.com
License: MIT
Requires-Dist: python-dotenv (>=1.0.0)
Requires-Dist: Pillow (>=9.0.0)
